{
	"id": "328ee6e8-f288-4c13-80b8-a40df8357116",
	"name": "Sportradar",
	"values": [
		{
			"key": "URL",
			"value": "https://reqres.in/api",
			"type": "default",
			"enabled": true
		},
		{
			"key": "TEST_NAME",
			"value": "test",
			"type": "default",
			"enabled": true
		},
		{
			"key": "TEST_JOB",
			"value": "test_job",
			"type": "default",
			"enabled": true
		},
		{
			"key": "USER_ID",
			"value": "",
			"type": "any",
			"enabled": true
		}
	],
	"_postman_variable_scope": "environment",
	"_postman_exported_at": "2024-08-16T18:58:42.432Z",
	"_postman_exported_using": "Postman/11.8.1"
}